soio/FuncMode.py
soio/__init__.py
soio/app.py
soio/algo/BBO.py
soio/algo/CGWO.py
soio/algo/CWOA.py
soio/algo/DE.py
soio/algo/GA.py
soio/algo/GWO.py
soio/algo/HS.py
soio/algo/ICA.py
soio/algo/JADE.py
soio/algo/MBO.py
soio/algo/SCEGWO.py
soio/algo/WOA.py
soio/algo/WOA1.py
soio/algo/__init__.py
soio/algo/discrete/GA.py
soio/algo/discrete/MBO.py
soio/algo/discrete/SCEGWO.py
soio/algo/discrete/__init__.py
soio/benchmark/Ackley.py
soio/benchmark/__init__.py
soio/core/__init__.py
soio/core/algorithm.py
soio/core/operator.py
soio/core/problem.py
soio/core/solution.py
soio/util/__init__.py
soio/util/benchmarks.py
soio-0.1.2.dist-info/LICENSE
soio-0.1.2.dist-info/METADATA
soio-0.1.2.dist-info/WHEEL
soio-0.1.2.dist-info/top_level.txt
soio-0.1.2.dist-info/RECORD
