Metadata-Version: 2.1
Name: soio
Version: 0.1.2
Summary: A single objective intelligent optimization package
Home-page: https://github.com/zzw95/SOIO
Author: Zhenwei Zhu
Author-email: zhuzhenwei95@gmail.com
License: UNKNOWN
Platform: UNKNOWN
Classifier: Programming Language :: Python :: 3
Classifier: License :: OSI Approved :: MIT License
Classifier: Operating System :: OS Independent
